LICENSE
MANIFEST.in
README.md
pyproject.toml
setup.py
PyQUDA_Utils.egg-info/PKG-INFO
PyQUDA_Utils.egg-info/SOURCES.txt
PyQUDA_Utils.egg-info/dependency_links.txt
PyQUDA_Utils.egg-info/entry_points.txt
PyQUDA_Utils.egg-info/requires.txt
PyQUDA_Utils.egg-info/top_level.txt
pyquda_io/__init__.py
pyquda_io/chroma.py
pyquda_io/ildg.py
pyquda_io/io_general.py
pyquda_io/io_utils.py
pyquda_io/kyu.py
pyquda_io/lime.py
pyquda_io/milc.py
pyquda_io/nersc.py
pyquda_io/npy.py
pyquda_io/openqcd.py
pyquda_io/xqcd.py
pyquda_plugins/__main__.py
pyquda_plugins/plugin_pyx.py
pyquda_plugins/pycontract/__init__.py
pyquda_plugins/pycparser/LICENSE
pyquda_plugins/pycparser/pycparser/__init__.py
pyquda_plugins/pycparser/pycparser/_ast_gen.py
pyquda_plugins/pycparser/pycparser/_build_tables.py
pyquda_plugins/pycparser/pycparser/_c_ast.cfg
pyquda_plugins/pycparser/pycparser/ast_transforms.py
pyquda_plugins/pycparser/pycparser/c_ast.py
pyquda_plugins/pycparser/pycparser/c_generator.py
pyquda_plugins/pycparser/pycparser/c_lexer.py
pyquda_plugins/pycparser/pycparser/c_parser.py
pyquda_plugins/pycparser/pycparser/plyparser.py
pyquda_plugins/pycparser/pycparser/ply/LICENSE
pyquda_plugins/pycparser/pycparser/ply/__init__.py
pyquda_plugins/pycparser/pycparser/ply/cpp.py
pyquda_plugins/pycparser/pycparser/ply/ctokens.py
pyquda_plugins/pycparser/pycparser/ply/lex.py
pyquda_plugins/pycparser/pycparser/ply/yacc.py
pyquda_plugins/pycparser/pycparser/ply/ygen.py
pyquda_plugins/pycparser/utils/fake_libc_include/_ansi.h
pyquda_plugins/pycparser/utils/fake_libc_include/_fake_defines.h
pyquda_plugins/pycparser/utils/fake_libc_include/_fake_typedefs.h
pyquda_plugins/pycparser/utils/fake_libc_include/_syslist.h
pyquda_plugins/pycparser/utils/fake_libc_include/aio.h
pyquda_plugins/pycparser/utils/fake_libc_include/alloca.h
pyquda_plugins/pycparser/utils/fake_libc_include/ar.h
pyquda_plugins/pycparser/utils/fake_libc_include/argz.h
pyquda_plugins/pycparser/utils/fake_libc_include/assert.h
pyquda_plugins/pycparser/utils/fake_libc_include/complex.h
pyquda_plugins/pycparser/utils/fake_libc_include/cpio.h
pyquda_plugins/pycparser/utils/fake_libc_include/ctype.h
pyquda_plugins/pycparser/utils/fake_libc_include/dirent.h
